strands_deepgram/__init__.py
strands_deepgram/deepgram.py
strands_deepgram-0.1.0.dist-info/licenses/LICENSE
strands_deepgram-0.1.0.dist-info/METADATA
strands_deepgram-0.1.0.dist-info/WHEEL
strands_deepgram-0.1.0.dist-info/top_level.txt
strands_deepgram-0.1.0.dist-info/RECORD
