Metadata-Version: 2.4
Name: strands-deepgram
Version: 0.1.0
Summary: Deepgram speech processing tool for Strands Agents SDK
Home-page: https://github.com/eraykeskinmac/strands-deepgram
Author: Eray Keskin
Author-email: Eray Keskin <eraykeskinmac@gmail.com>
License: MIT
Project-URL: Homepage, https://github.com/eraykeskinmac/strands-deepgram
Project-URL: Documentation, https://github.com/eraykeskinmac/strands-deepgram
Project-URL: Repository, https://github.com/eraykeskinmac/strands-deepgram
Project-URL: Bug Reports, https://github.com/eraykeskinmac/strands-deepgram/issues
Keywords: strands,ai,agents,deepgram,speech-to-text,text-to-speech,audio-intelligence
Classifier: Development Status :: 4 - Beta
Classifier: Intended Audience :: Developers
Classifier: License :: OSI Approved :: MIT License
Classifier: Programming Language :: Python :: 3
Classifier: Programming Language :: Python :: 3.9
Classifier: Programming Language :: Python :: 3.10
Classifier: Programming Language :: Python :: 3.11
Classifier: Programming Language :: Python :: 3.12
Classifier: Topic :: Software Development :: Libraries :: Python Modules
Classifier: Topic :: Scientific/Engineering :: Artificial Intelligence
Requires-Python: >=3.9
License-File: LICENSE
Requires-Dist: strands-agents>=1.11.0
Requires-Dist: deepgram-sdk>=3.0.0
Requires-Dist: requests>=2.31.0
Requires-Dist: rich>=13.0.0
Provides-Extra: dev
Requires-Dist: pytest>=7.0.0; extra == "dev"
Requires-Dist: black>=23.0.0; extra == "dev"
Requires-Dist: flake8>=6.0.0; extra == "dev"
Dynamic: author
Dynamic: home-page
Dynamic: license-file
Dynamic: requires-python
